cython_direct/_compute.cpython-313-darwin.so
mandelbrot_implementations_cython_direct.dylibs/libomp.dylib
mandelbrot_implementations_cython_direct-0.1.0.dist-info/RECORD
mandelbrot_implementations_cython_direct-0.1.0.dist-info/WHEEL
mandelbrot_implementations_cython_direct-0.1.0.dist-info/top_level.txt
mandelbrot_implementations_cython_direct-0.1.0.dist-info/METADATA
